deepsim/__init__.py
deepsim/deep_similarity.py
deepsim/__pycache__/__init__.cpython-39.pyc
deepsim/__pycache__/deep_similarity.cpython-39.pyc
deepsim-0.0.1a0.dist-info/LICENSE
deepsim-0.0.1a0.dist-info/METADATA
deepsim-0.0.1a0.dist-info/WHEEL
deepsim-0.0.1a0.dist-info/top_level.txt
deepsim-0.0.1a0.dist-info/RECORD
