Metadata-Version: 2.1
Name: deepsim
Version: 0.0.1a0
Summary: This toolkit provides deep learning-based similarity utilities.
Home-page: https://github.com/dhchenx/deepsim
Author: Donghua Chen
Author-email: douglaschan@126.com
License: BSD-3
Project-URL: Bug Reports, https://github.com/dhchenx/deepsim/issues
Project-URL: Source, https://github.com/dhchenx/deepsim
Keywords: text similarity
Classifier: Development Status :: 5 - Production/Stable
Classifier: Intended Audience :: Developers
Classifier: Topic :: Software Development :: Build Tools
Classifier: License :: OSI Approved :: MIT License
Classifier: Programming Language :: Python :: 3
Classifier: Programming Language :: Python :: 3.6
Classifier: Programming Language :: Python :: 3.7
Classifier: Programming Language :: Python :: 3.8
Classifier: Programming Language :: Python :: 3.9
Classifier: Programming Language :: Python :: 3 :: Only
Requires-Python: >=3.6, <4
License-File: LICENSE
Requires-Dist: text2vec
Provides-Extra: dev
Requires-Dist: check-manifest ; extra == 'dev'
Provides-Extra: test
Requires-Dist: coverage ; extra == 'test'
